v_time/__init__.py
v_time/v_time.py
v_time-1.2.0.dist-info/LICENSE.txt
v_time-1.2.0.dist-info/METADATA
v_time-1.2.0.dist-info/WHEEL
v_time-1.2.0.dist-info/top_level.txt
v_time-1.2.0.dist-info/RECORD
