Metadata-Version: 2.1
Name: v-time
Version: 1.2.0
Summary: Time related functions
Home-page: https://github.com/villoro/v-time
Author: Arnau Villoro
Author-email: arnau@villoro.com
License: MIT
Platform: UNKNOWN
Classifier: Intended Audience :: Developers
Classifier: Intended Audience :: Education
Classifier: Intended Audience :: Manufacturing
Classifier: Intended Audience :: Science/Research
Classifier: License :: OSI Approved :: MIT License
Classifier: Programming Language :: Python
Classifier: Programming Language :: Python :: 3.6
